promptsy/__init__.py
promptsy/auto_few_shot_generator.py
promptsy/prompt.py
promptsy/prompt_enhancer.py
promptsy/prompt_manager.py
tests/__init__.py
tests/test_prompt.py
tests/test_prompt_manager.py
promptsy-0.1.3.6.dist-info/LICENSE
promptsy-0.1.3.6.dist-info/METADATA
promptsy-0.1.3.6.dist-info/WHEEL
promptsy-0.1.3.6.dist-info/top_level.txt
promptsy-0.1.3.6.dist-info/RECORD
