Metadata-Version: 2.1
Name: promptsy
Version: 0.1.3.6
Summary: A Python library for managing and organizing prompts for Large Language Models (LLMs)
Home-page: https://github.com/feliperafael/promptsy
Author: Felipe Rafael de Souza
Author-email: felipe@evakub.com.br
Keywords: prompts llm-prompts prompt-management large-language-models
Classifier: Development Status :: 3 - Alpha
Classifier: Intended Audience :: Developers
Classifier: License :: OSI Approved :: MIT License
Classifier: Programming Language :: Python :: 3
Classifier: Programming Language :: Python :: 3.6
Classifier: Programming Language :: Python :: 3.7
Classifier: Programming Language :: Python :: 3.8
Classifier: Programming Language :: Python :: 3.9
Classifier: Topic :: Scientific/Engineering :: Artificial Intelligence
Classifier: Topic :: Software Development :: Libraries :: Python Modules
License-File: LICENSE
Requires-Dist: pydantic >=2.8.2
Requires-Dist: colorama
Requires-Dist: openai >=1.44.1
